{
  "metadata": {
    "input_documents": [
      "Gopi Mekala Updated Resume Node+Flutter.pdf",
      "Flutter Developer Roadmap.pdf",
      "Nodejs_Developer_Roadmap.pdf",
      "06378fd2-7374-4b4c-9607-59ae228d7635_295be27d-d015-42fd-9860-fb6cc7026b47_python cheat sheet-1.pdf"
    ],
    "persona_role": "software",
    "persona_focus_keywords": [
      "beural"
    ],
    "job_to_be_done": "prepapre",
    "processing_timestamp": "2025-07-27T11:28:28.803197+00:00"
  },
  "ranked_sections": []
}